README.txt
plonetheme.solemnity-configure.zcml
pypi_upload.sh
setup.py
docs/HISTORY.txt
docs/INSTALL.txt
docs/LICENSE.GPL
docs/LICENSE.txt
plonetheme/__init__.py
plonetheme.solemnity.egg-info/PKG-INFO
plonetheme.solemnity.egg-info/SOURCES.txt
plonetheme.solemnity.egg-info/dependency_links.txt
plonetheme.solemnity.egg-info/entry_points.txt
plonetheme.solemnity.egg-info/namespace_packages.txt
plonetheme.solemnity.egg-info/not-zip-safe
plonetheme.solemnity.egg-info/requires.txt
plonetheme.solemnity.egg-info/top_level.txt
plonetheme/solemnity/__init__.py
plonetheme/solemnity/configure.zcml
plonetheme/solemnity/profiles.zcml
plonetheme/solemnity/setuphandlers.py
plonetheme/solemnity/skins.zcml
plonetheme/solemnity/tests.py
plonetheme/solemnity/browser/__init__.py
plonetheme/solemnity/browser/configure.zcml
plonetheme/solemnity/browser/interfaces.py
plonetheme/solemnity/browser/viewlet.pt
plonetheme/solemnity/browser/viewlets.py
plonetheme/solemnity/browser/images/CONTENT.txt
plonetheme/solemnity/browser/images/README.txt
plonetheme/solemnity/browser/images/body.jpg
plonetheme/solemnity/browser/images/content.jpg
plonetheme/solemnity/browser/images/description.jpg
plonetheme/solemnity/browser/images/h1.gif
plonetheme/solemnity/browser/images/h2.jpg
plonetheme/solemnity/browser/images/nav_a_hover.jpg
plonetheme/solemnity/browser/images/sidebar.jpg
plonetheme/solemnity/browser/images/wrapper2.jpg
plonetheme/solemnity/browser/stylesheets/README.txt
plonetheme/solemnity/browser/stylesheets/main.css
plonetheme/solemnity/browser/templates/news.pt
plonetheme/solemnity/profiles/default/cssregistry.xml
plonetheme/solemnity/profiles/default/import_steps.xml
plonetheme/solemnity/profiles/default/jsregistry.xml
plonetheme/solemnity/profiles/default/plonetheme.solemnity_various.txt
plonetheme/solemnity/profiles/default/skins.xml
plonetheme/solemnity/profiles/default/viewlets.xml
plonetheme/solemnity/skins/plonetheme_solemnity_custom_images/CONTENT.txt
plonetheme/solemnity/skins/plonetheme_solemnity_custom_templates/CONTENT.txt
plonetheme/solemnity/skins/plonetheme_solemnity_custom_templates/main_template.pt
plonetheme/solemnity/skins/plonetheme_solemnity_styles/CONTENT.txt
plonetheme/solemnity/skins/plonetheme_solemnity_styles/authoring.css.dtml
plonetheme/solemnity/skins/plonetheme_solemnity_styles/base.css.dtml
