Metadata-Version: 1.0
Name: plonetheme.solemnity
Version: 0.7
Summary: An installable theme for Plone 3.0 based on the solemnity theme by Six Shooter Media.
Home-page: http://svn.plone.org/svn/collective/plonetheme.solemnity
Author: Timo Stollenwerk
Author-email: timo@zmag.de
License: GPL
Keywords: web zope plone theme
Platform: UNKNOWN
Classifier: Framework :: Plone
Classifier: Framework :: Zope2
Classifier: Framework :: Zope3
Classifier: Programming Language :: Python
Classifier: Topic :: Software Development :: Libraries :: Python Modules
